w3multicall/__init__.py
w3multicall/multicall.py
w3multicall/threading/__init__.py
w3multicall/threading/w3multicall_executor.py
w3multicall/w3/__init__.py
w3multicall/w3/w3.py
w3multicall-0.3.1.dist-info/LICENSE
w3multicall-0.3.1.dist-info/METADATA
w3multicall-0.3.1.dist-info/WHEEL
w3multicall-0.3.1.dist-info/top_level.txt
w3multicall-0.3.1.dist-info/RECORD
