Metadata-Version: 2.1
Name: w3multicall
Version: 0.3.1
Summary: Python interface and utilities for Solidity multicall contract
Home-page: https://github.com/0rtis/w3multicall
Author: Ortis
Author-email: Ortis <ortis@ortis.io>
License: MIT License
Keywords: blockchain,web3,etherum,solidity
Classifier: Development Status :: 4 - Beta
Classifier: Environment :: Console
Classifier: Programming Language :: Python :: 3
Requires-Python: >=3.8
License-File: LICENSE
Requires-Dist: requests
Requires-Dist: web3
Requires-Dist: importlib-metadata ; python_version < "3.8"
